README.md
setup.cfg
setup.py
nextcord_logging/__init__.py
nextcord_logging/nextcord_logging.py
nextcord_logging.egg-info/PKG-INFO
nextcord_logging.egg-info/SOURCES.txt
nextcord_logging.egg-info/dependency_links.txt
nextcord_logging.egg-info/requires.txt
nextcord_logging.egg-info/top_level.txt