Metadata-Version: 2.1
Name: nextcord-logging
Version: 1.0
Summary: An exact copy of discord-logging but for Nextcord.
Author: Avaneesh Sharma
Author-email: super.avaneesh@gmail.com
Classifier: Programming Language :: Python
Classifier: Programming Language :: Python :: 3
Classifier: Operating System :: OS Independent
Classifier: Topic :: Utilities
Classifier: Intended Audience :: Developers
Requires-Python: >=3.6
